cronverter/__init__.py
cronverter/constants.py
cronverter/quartz2unix.py
cronverter-0.2.0.dist-info/licenses/LICENSE
cronverter-0.2.0.dist-info/METADATA
cronverter-0.2.0.dist-info/WHEEL
cronverter-0.2.0.dist-info/top_level.txt
cronverter-0.2.0.dist-info/RECORD
